cytocraft/__init__.py
cytocraft/craft.py
cytocraft/model.py
cytocraft/plot.py
cytocraft/rigid.py
cytocraft/shape.py
cytocraft/simulation.py
cytocraft/stereopy.py
cytocraft/util.py
cytocraft/gtf/AmexT_v47-AmexG_v6.0-DD.gene.gtf
cytocraft/gtf/gencode.v44.basic.annotation.gene.gtf
cytocraft/gtf/gencode.vM34.annotation.gene.gtf
cytocraft/gtf/mice_genes.gtf
cytocraft-0.1.dist-info/METADATA
cytocraft-0.1.dist-info/WHEEL
cytocraft-0.1.dist-info/licenses/LICENSE
cytocraft-0.1.dist-info/RECORD
