Metadata-Version: 2.3
Name: cytocraft
Version: 0.1
Summary: The Cytocraft package provides prediction of chromosome conformation based on spatial transcriptomic.
Project-URL: Homepage, https://github.com/YifeiSheng/Cytocraft
Project-URL: Issues, https://github.com/YifeiSheng/Cytocraft/issues
Project-URL: Repository, https://github.com/YifeiSheng/Cytocraft.git
Author-email: Yifei Sheng <yfsheng6@gmail.com>, Shiying Li <shiyingli7-c@my.cityu.edu.hk>, Shuai Cheng Li <sc.li@cityu.edu.hk>
License: MIT license
License-File: LICENSE
Classifier: Development Status :: 4 - Beta
Classifier: Intended Audience :: Science/Research
Classifier: License :: OSI Approved :: MIT License
Classifier: Operating System :: OS Independent
Classifier: Programming Language :: Python :: 3.8
Classifier: Topic :: Scientific/Engineering :: Bio-Informatics
Requires-Python: >=3.8
Requires-Dist: scanpy
Requires-Dist: shapely
